caelestis/__init__.py
caelestis/main.py
caelestis-0.4.2.dist-info/LICENSE
caelestis-0.4.2.dist-info/METADATA
caelestis-0.4.2.dist-info/WHEEL
caelestis-0.4.2.dist-info/entry_points.txt
caelestis-0.4.2.dist-info/top_level.txt
caelestis-0.4.2.dist-info/RECORD
