Metadata-Version: 2.1
Name: caelestis
Version: 0.4.2
Summary: Knowledge management system.
Home-page: https://github.com/lucasmaystre/caelestis
Author: Lucas Maystre
Author-email: lucas@maystre.ch
License: MIT
Keywords: zettelkasten knowledge information notes
Classifier: Development Status :: 3 - Alpha
Classifier: Environment :: Console
Classifier: License :: OSI Approved :: MIT License
Classifier: Programming Language :: Python :: 3
Requires-Python: >=3.6
License-File: LICENSE
Requires-Dist: sh
Requires-Dist: Click
